maleo/soma/models/__init__.py
maleo/soma/models/table.py
maleo/soma/models/mixins/__init__.py
maleo/soma/models/mixins/identifier.py
maleo/soma/models/mixins/status.py
maleo/soma/models/mixins/timestamp.py
maleo_soma_models-0.0.2.dist-info/licenses/LICENSE
maleo_soma_models-0.0.2.dist-info/METADATA
maleo_soma_models-0.0.2.dist-info/WHEEL
maleo_soma_models-0.0.2.dist-info/top_level.txt
maleo_soma_models-0.0.2.dist-info/RECORD
