Metadata-Version: 2.4
Name: maleo-soma-models
Version: 0.0.2
Summary: Soma models package for MaleoSuite
Author-email: Agra Bima Yuda <agra@nexmedis.com>
License: Proprietary
Requires-Python: >=3.12
License-File: LICENSE
Requires-Dist: annotated-types>=0.7.0
Requires-Dist: anyio>=4.10.0
Requires-Dist: black>=25.1.0
Requires-Dist: cachetools>=5.5.2
Requires-Dist: cffi>=1.17.1
Requires-Dist: cfgv>=3.4.0
Requires-Dist: click>=8.2.1
Requires-Dist: cryptography>=45.0.6
Requires-Dist: distlib>=0.4.0
Requires-Dist: fastapi>=0.116.1
Requires-Dist: filelock>=3.19.1
Requires-Dist: google-auth>=2.40.3
Requires-Dist: greenlet>=3.2.4
Requires-Dist: identify>=2.6.13
Requires-Dist: idna>=3.10
Requires-Dist: maleo-soma-enums>=0.0.7
Requires-Dist: maleo-soma-types-base>=0.0.4
Requires-Dist: maleo-soma-utils>=0.0.5
Requires-Dist: mypy_extensions>=1.1.0
Requires-Dist: nodeenv>=1.9.1
Requires-Dist: packaging>=25.0
Requires-Dist: pathspec>=0.12.1
Requires-Dist: platformdirs>=4.4.0
Requires-Dist: pre_commit>=4.3.0
Requires-Dist: pyasn1>=0.6.1
Requires-Dist: pyasn1_modules>=0.4.2
Requires-Dist: pycparser>=2.22
Requires-Dist: pycryptodome>=3.23.0
Requires-Dist: pydantic>=2.11.7
Requires-Dist: pydantic_core>=2.33.2
Requires-Dist: PyYAML>=6.0.2
Requires-Dist: rsa>=4.9.1
Requires-Dist: sniffio>=1.3.1
Requires-Dist: SQLAlchemy>=2.0.43
Requires-Dist: starlette>=0.47.3
Requires-Dist: typing-inspection>=0.4.1
Requires-Dist: typing_extensions>=4.15.0
Requires-Dist: virtualenv>=20.34.0
Dynamic: license-file
